mahlzeit/__init__.py
mahlzeit-0.9.6.dist-info/LICENSE
mahlzeit-0.9.6.dist-info/METADATA
mahlzeit-0.9.6.dist-info/WHEEL
mahlzeit-0.9.6.dist-info/top_level.txt
mahlzeit-0.9.6.dist-info/RECORD
