Metadata-Version: 2.1
Name: mahlzeit
Version: 0.9.6
Summary: Mahlzeit Plaintextaccounting für Essen und Anderes
Home-page: https://gitlab.com/meschenbacher/mahlzeit
Author: Maximilian Eschenbacher
Author-email: qbzioxli@m.t.kajt.de
License: UNKNOWN
Platform: UNKNOWN
Classifier: Programming Language :: Python :: 3
Classifier: Operating System :: OS Independent
Requires-Python: >=3
